{
  "name": "bookstack",
  "plugin_schema": "2",
  "release": "11.3-RELEASE",
  "artifact": "https://github.com/Adirael/iocage-plugin-bookstack.git",
  "pkgs": [
    "git",
    "nginx",
    "openssl",
    "mariadb102-server",
    "php73",
    "php73-tidy",
    "php73-tokenizer",
    "php73-openssl",
    "php73-pdo",
    "php73-mysqli",
    "php73-simplexml",
    "php73-mbstring"
  ],
  "packagesite": "http://pkg.FreeBSD.org/FreeBSD:11:amd64/latest",
  "fingerprints": {
    "iocage-plugins": [
      {
      "function": "sha256",
      "fingerprint": "b0170035af3acc5f3f3ae1859dc717101b4e6c1d0a794ad554928ca0cbb2f438"
      }
    ]
  },
  "official": false
}
